inelsmqtt/__init__.py
inelsmqtt/config.py
inelsmqtt/const.py
inelsmqtt/discovery.py
inelsmqtt/mqtt_client.py
inelsmqtt/util.py
inelsmqtt/devices/__init__.py
inelsmqtt/devices/switch.py
tests/__init__.py
tests/const.py
tests/discovery_test.py
tests/inels_mqtt_test.py
tests/online_test.py
tests/devices/__init__.py
tests/devices/device_test.py
inels_mqtt_new-0.2.23.dist-info/LICENSE
inels_mqtt_new-0.2.23.dist-info/METADATA
inels_mqtt_new-0.2.23.dist-info/WHEEL
inels_mqtt_new-0.2.23.dist-info/top_level.txt
inels_mqtt_new-0.2.23.dist-info/RECORD
