Metadata-Version: 2.1
Name: inels-mqtt-new
Version: 0.2.23
Summary: Python library for iNELS mqtt protocol
Home-page: https://github.com/zed4805/inels-mqtt-new
Author: Elko EP s.r.o.
Author-email: zed4805@gmail.com
License: MIT
Keywords: iNels,Elko EP,Home assistant integration
Classifier: License :: OSI Approved :: MIT License
Classifier: Programming Language :: Python :: 3
Classifier: Programming Language :: Python :: 3.9
License-File: LICENSE
